README.md
setup.cfg
setup.py
distributions_AMG11/Binomialdistribution.py
distributions_AMG11/Gaussiandistribution.py
distributions_AMG11/Generaldistribution.py
distributions_AMG11/__init__.py
distributions_AMG11.egg-info/PKG-INFO
distributions_AMG11.egg-info/SOURCES.txt
distributions_AMG11.egg-info/dependency_links.txt
distributions_AMG11.egg-info/not-zip-safe
distributions_AMG11.egg-info/top_level.txt